
{
    "item":[
            {
             "title": "더스타 The Star 2018.6.7 (앞표지 : 윤시윤 / 뒤표지 : 아스트로) - 합본호, 주요기사 : 윤시윤 화보 10p, 워너원 기자간담회 8p, 아스트로 화보 10p, 카라 출신 니콜 컴백 화보 6p, 배우 송강 4p",
             "link": "http://www.aladin.co.kr/shop/wproduct.aspx?ItemId=149549966&amp;partner=openAPI&amp;start=api",
             "author": "더 스타 편집부 (지은이)",
             "pubDate": "2018-06-08",
             "description": "",
             "isbn": "K672533962",
             "isbn13": "",
             "itemId": 149549966,
             "priceSales": 3150,
             "priceStandard": 3500,
             "mallType": "BOOK",
             "stockStatus": "예약판매",
             "mileage": 25,
             "cover": "http://image.aladin.co.kr/product/14954/99/coversum/k672533962_1.jpg",
             "categoryId": 69436,
             "categoryName": "국내도서>잡지>여성/남성/패션>패션/여성지",
             "publisher": "더스타아시아(잡지)",
             "salesPoint": 0,
             "fixedPrice": false,
             "customerReviewRank": 0,
             "subInfo": {}
             },
             {
             "title": "타인의 시선 - 국부에서 협상가까지, 대한민국 대통령",
             "link": "http://www.aladin.co.kr/shop/wproduct.aspx?ItemId=149549953&amp;partner=openAPI&amp;start=api",
             "author": "타임TIME, 찰리 캠벨 (지은이), 배현 (옮긴이)",
             "pubDate": "2018-06-11",
             "description": "세계적으로 가장 영향력 높은 시사지 &lt;타임TIME&gt;의 눈으로 바라본 우리 현대사를 조망한다. 1950년 10월 16일부터 2017년 5월 15일까지, 70년 가까이 한국 현대사와 함께한 &lt;타임&gt; 커버를 장식한 기사를 포함, 총 12개의 기사를 수록했다.",
             "isbn": "8976130502",
             "isbn13": "9788976130501",
             "itemId": 149549953,
             "priceSales": 16200,
             "priceStandard": 18000,
             "mallType": "BOOK",
             "stockStatus": "",
             "mileage": 55,
             "cover": "http://image.aladin.co.kr/product/14954/99/coversum/8976130502_1.jpg",
             "categoryId": 51220,
             "categoryName": "국내도서>사회과학>정치학/외교학/행정학>정치인",
             "publisher": "유피에이(UPA)",
             "salesPoint": 0,
             "fixedPrice": true,
             "customerReviewRank": 10,
             "subInfo": {}
             },
             {
             "title": "최하위 직업에서 최강까지 출세하다 1 - L Books",
             "link": "http://www.aladin.co.kr/shop/wproduct.aspx?ItemId=149549567&amp;partner=openAPI&amp;start=api",
             "author": "카미타니 케이 (지은이), 쿠와시마 레인 (그림), 안병훈 (옮긴이)",
             "pubDate": "2018-06-20",
             "description": "최하위 직업인 『저급 마도사』로서 시원치 않은 나날을 보내던 소년 루크. 하지만 어떤 사건을 계기로 그를 둘러싼 환경은 크게 변화하기 시작한다. 그 사건은 「포위섬멸진」이라는 진형을 고안함으로써 그 이름을 전쟁의 역사에 새기게 되는 그의 시작에 불과했다.",
             "isbn": "K662533962",
             "isbn13": "9791127845117",
             "itemId": 149549567,
             "priceSales": 8820,
             "priceStandard": 9800,
             "mallType": "BOOK",
             "stockStatus": "예약판매",
             "mileage": 37,
             "cover": "http://image.aladin.co.kr/product/14954/95/coversum/k662533962_1.jpg",
             "categoryId": 130122,
             "categoryName": "국내도서>소설/시/희곡>라이트 노벨>L 북스",
             "publisher": "디앤씨미디어(주)(D&C미디어)",
             "salesPoint": 0,
             "fixedPrice": true,
             "customerReviewRank": 6,
             "subInfo": {}
             },
             {
             "title": "우리 딸을 위해서라면, 나는 마왕도 쓰러뜨릴 수 있을지 몰라 7 드라마 CD (특별판) - L Books",
             "link": "http://www.aladin.co.kr/shop/wproduct.aspx?ItemId=149549252&amp;partner=openAPI&amp;start=api",
             "author": "CHIROLU (지은이), Kei (그림), 송재희 (옮긴이)",
             "pubDate": "2018-06-20",
             "description": "정든 크로이츠로 무사히 돌아와 평온한 일상을 되찾은 데일과 라티나. 귀환 후, 특히 라티나를 기쁘게 한 것은 크로이츠에서 먹는 맛있는 밥이었다. 그리고 밝혀지는 마인족 나라의 너무나 유감스러운 식생활. 조금이라도 맛있는 음식을 먹고 싶은 라티나는 남몰래 어떤 요리에 도전한다.",
             "isbn": "K542533962",
             "isbn13": "9791127845438",
             "itemId": 149549252,
             "priceSales": 26820,
             "priceStandard": 29800,
             "mallType": "BOOK",
             "stockStatus": "예약판매",
             "mileage": 95,
             "cover": "http://image.aladin.co.kr/product/14954/92/coversum/k542533962_1.jpg",
             "categoryId": 130122,
             "categoryName": "국내도서>소설/시/희곡>라이트 노벨>L 북스",
             "publisher": "디앤씨미디어(주)(D&C미디어)",
             "salesPoint": 0,
             "fixedPrice": true,
             "customerReviewRank": 10,
             "subInfo": {}
             },
             {
             "title": "우리 딸을 위해서라면, 나는 마왕도 쓰러뜨릴 수 있을지 몰라 7 - L Books",
             "link": "http://www.aladin.co.kr/shop/wproduct.aspx?ItemId=149549136&amp;partner=openAPI&amp;start=api",
             "author": "CHIROLU (지은이), Kei (그림), 송재희 (옮긴이)",
             "pubDate": "2018-06-20",
             "description": "복슬복슬 성분 대폭 증가?! 크로이츠의 일상은 행복과 함께! 마인족의 나라에서 정든 크로이츠로 무사히 돌아와 평온한 일상을 되찾은 데일과 라티나. 귀환 후, 특히 라티나를 기쁘게 한 것은……",
             "isbn": "K532533962",
             "isbn13": "9791127845360",
             "itemId": 149549136,
             "priceSales": 8820,
             "priceStandard": 9800,
             "mallType": "BOOK",
             "stockStatus": "예약판매",
             "mileage": 35,
             "cover": "http://image.aladin.co.kr/product/14954/91/coversum/k532533962_1.jpg",
             "categoryId": 130122,
             "categoryName": "국내도서>소설/시/희곡>라이트 노벨>L 북스",
             "publisher": "디앤씨미디어(주)(D&C미디어)",
             "salesPoint": 0,
             "fixedPrice": true,
             "customerReviewRank": 10,
             "subInfo": {}
             },
             {
             "title": "주삶 2018.7.8 (개역개정본문) - 주야로 묵상하는 삶",
             "link": "http://www.aladin.co.kr/shop/wproduct.aspx?ItemId=149548214&amp;partner=openAPI&amp;start=api",
             "author": "주삶편집위원회 (지은이)",
             "pubDate": "2018-07-01",
             "description": "큐티를 하긴 해야 할텐데 어떻게 해야 될지 모르신다면, 큐티를 하고 있긴 하지만 좀더 깊이있고 체계적인 묵상을 원하신다면, &lt;주삶&gt;을 권한다.",
             "isbn": "K572533962",
             "isbn13": "9772287684006",
             "itemId": 149548214,
             "priceSales": 4750,
             "priceStandard": 5000,
             "mallType": "BOOK",
             "stockStatus": "",
             "mileage": 23,
             "cover": "http://image.aladin.co.kr/product/14954/82/coversum/k572533962_1.jpg",
             "categoryId": 3125,
             "categoryName": "국내도서>잡지>종교",
             "publisher": "아가페출판사(잡지)",
             "salesPoint": 0,
             "fixedPrice": false,
             "customerReviewRank": 0,
             "subInfo": {}
             },
             {
             "title": "카카오 농부는 왜 초콜릿을 사 먹지 못할까? - 생산자와 소비자가 함께 웃는 공정무역 이야기",
             "link": "http://www.aladin.co.kr/shop/wproduct.aspx?ItemId=149544106&amp;partner=openAPI&amp;start=api",
             "author": "카리 존스 (지은이), 현혜진 (옮긴이)",
             "pubDate": "2018-05-25",
             "description": "",
             "isbn": "K452533962",
             "isbn13": "9791157820665",
             "itemId": 149544106,
             "priceSales": 9450,
             "priceStandard": 10500,
             "mallType": "BOOK",
             "stockStatus": "",
             "mileage": 30,
             "cover": "http://image.aladin.co.kr/product/14954/41/coversum/k452533962_1.jpg",
             "categoryId": 48907,
             "categoryName": "국내도서>어린이>사회/역사/철학>인권/평등",
             "publisher": "초록개구리",
             "salesPoint": 0,
             "fixedPrice": true,
             "customerReviewRank": 0,
             "subInfo": {}
             },
             {
             "title": "머리가 좋은 골퍼.나쁜 골퍼 - 누구나 10타 줄이는 골프 레슨",
             "link": "http://www.aladin.co.kr/shop/wproduct.aspx?ItemId=149543741&amp;partner=openAPI&amp;start=api",
             "author": "라이프 엑스퍼트 (지은이), 서영 (옮긴이)",
             "pubDate": "2018-06-20",
             "description": "일본에서 처음 출간한 뒤 현재까지 꾸준하게 사랑을 받고 있는 골프 교습서의 스테디셀러이다. 싱글 골퍼가 되기 위해 반드시 알아야 하는 코스 매니지먼트의 노하우를 전수하며, 책을 통해 골프가 단순히 체력만이 아니라 전략이 중요한 게임이라는 사실을 일깨운다.",
             "isbn": "K262533962",
             "isbn13": "9791187113263",
             "itemId": 149543741,
             "priceSales": 12600,
             "priceStandard": 14000,
             "mallType": "BOOK",
             "stockStatus": "",
             "mileage": 43,
             "cover": "http://image.aladin.co.kr/product/14954/37/coversum/k262533962_1.jpg",
             "categoryId": 53524,
             "categoryName": "국내도서>건강/취미/레저>골프",
             "publisher": "이아소",
             "salesPoint": 0,
             "fixedPrice": true,
             "customerReviewRank": 0,
             "subInfo": {}
             },
             {
             "title": "리얼 로봇공학자",
             "link": "http://www.aladin.co.kr/shop/wproduct.aspx?ItemId=149543733&amp;partner=openAPI&amp;start=api",
             "author": "&lt;MODU&gt; 매거진, 박지은 (지은이)",
             "pubDate": "2018-06-18",
             "description": "",
             "isbn": "8957369597",
             "isbn13": "9788957369593",
             "itemId": 149543733,
             "priceSales": 11700,
             "priceStandard": 13000,
             "mallType": "BOOK",
             "stockStatus": "",
             "mileage": 41,
             "cover": "http://image.aladin.co.kr/product/14954/37/coversum/8957369597_1.jpg",
             "categoryId": 2012,
             "categoryName": "국내도서>청소년>청소년의 진로선택",
             "publisher": "가나출판사",
             "salesPoint": 0,
             "fixedPrice": true,
             "customerReviewRank": 0,
             "subInfo": {}
             },
             {
             "title": "착하게 살아온 나날",
             "link": "http://www.aladin.co.kr/shop/wproduct.aspx?ItemId=149543257&amp;partner=openAPI&amp;start=api",
             "author": "조지 고든 바이런 (지은이), 피천득 (옮긴이)",
             "pubDate": "2018-06-05",
             "description": "",
             "isbn": "8937475316",
             "isbn13": "9788937475313",
             "itemId": 149543257,
             "priceSales": 9000,
             "priceStandard": 10000,
             "mallType": "BOOK",
             "stockStatus": "",
             "mileage": 31,
             "cover": "http://image.aladin.co.kr/product/14954/32/coversum/8937475316_1.jpg",
             "categoryId": 51168,
             "categoryName": "국내도서>소설/시/희곡>시>외국시",
             "publisher": "민음사",
             "salesPoint": 0,
             "fixedPrice": true,
             "customerReviewRank": 0,
             "subInfo": {}
             }
            ]
}

